[
  {"disease_id": "DIS001", "disease_name": "stroke",                   "severity": "EMERGENCY", "description": "A stroke occurs when blood supply to part of the brain is cut off",                                    "symptoms": ["sudden severe headache", "face drooping", "arm weakness", "speech difficulty", "vision loss", "confusion", "dizziness", "loss of balance", "numbness"]},
  {"disease_id": "DIS002", "disease_name": "heart attack",             "severity": "EMERGENCY", "description": "A heart attack occurs when blood flow to the heart is blocked",                                        "symptoms": ["chest pain", "chest pressure", "shortness of breath", "pain in left arm", "cold sweat", "nausea", "dizziness", "jaw pain", "fatigue"]},
  {"disease_id": "DIS003", "disease_name": "severe allergic reaction", "severity": "EMERGENCY", "description": "Anaphylaxis is a severe, potentially life-threatening allergic reaction",                              "symptoms": ["difficulty breathing", "swelling of throat", "swelling of face", "rapid heartbeat", "dizziness", "skin rash", "nausea", "low blood pressure"]},
  {"disease_id": "DIS004", "disease_name": "pneumonia",                "severity": "URGENT",    "description": "Pneumonia is an infection that inflames the air sacs in the lungs",                                   "symptoms": ["high fever", "cough", "difficulty breathing", "chest pain", "fatigue", "confusion", "chills", "sweating"]},
  {"disease_id": "DIS005", "disease_name": "deep vein thrombosis",     "severity": "URGENT",    "description": "DVT is a blood clot in a deep vein, usually in the leg",                                             "symptoms": ["leg swelling", "leg pain", "warmth in leg", "redness in leg", "cramping"]},
  {"disease_id": "DIS006", "disease_name": "urinary tract infection",  "severity": "URGENT",    "description": "UTI is an infection in any part of the urinary system",                                               "symptoms": ["burning urination", "frequent urination", "cloudy urine", "fever", "lower abdominal pain", "blood in urine"]},
  {"disease_id": "DIS007", "disease_name": "diabetes complications",   "severity": "MONITOR",   "description": "Uncontrolled diabetes can lead to various complications",                                             "symptoms": ["excessive thirst", "frequent urination", "blurry vision", "fatigue", "slow healing wounds", "tingling in hands", "tingling in feet", "weight loss"]},
  {"disease_id": "DIS008", "disease_name": "hypertension crisis",      "severity": "URGENT",    "description": "Hypertensive crisis occurs when blood pressure reaches dangerously high levels",                       "symptoms": ["severe headache", "blurry vision", "dizziness", "nausea", "nosebleed", "shortness of breath", "chest pain"]},
  {"disease_id": "DIS009", "disease_name": "arthritis flare",          "severity": "MONITOR",   "description": "An arthritis flare is a period of increased disease activity",                                        "symptoms": ["joint pain", "joint stiffness", "joint swelling", "reduced range of motion", "warmth around joint", "fatigue"]},
  {"disease_id": "DIS010", "disease_name": "gastroenteritis",          "severity": "MONITOR",   "description": "Gastroenteritis is inflammation of the stomach and intestines",                                       "symptoms": ["diarrhea", "nausea", "vomiting", "stomach cramps", "fever", "headache", "muscle aches"]},
  {"disease_id": "DIS011", "disease_name": "common cold",              "severity": "NORMAL",    "description": "The common cold is a viral infection of the upper respiratory tract",                                 "symptoms": ["runny nose", "sneezing", "sore throat", "mild cough", "mild headache", "mild fever", "body aches"]},
  {"disease_id": "DIS012", "disease_name": "seasonal allergy",         "severity": "NORMAL",    "description": "Seasonal allergies are immune responses to outdoor allergens",                                         "symptoms": ["sneezing", "runny nose", "itchy eyes", "watery eyes", "nasal congestion", "itchy throat"]},
  {"disease_id": "DIS013", "disease_name": "mild dehydration",         "severity": "MONITOR",   "description": "Dehydration occurs when you use or lose more fluid than you take in",                                 "symptoms": ["dry mouth", "thirst", "dark urine", "fatigue", "dizziness", "headache"]},
  {"disease_id": "DIS014", "disease_name": "insomnia",                 "severity": "NORMAL",    "description": "Insomnia is a sleep disorder where you have trouble falling or staying asleep",                       "symptoms": ["difficulty sleeping", "waking up at night", "fatigue", "irritability", "difficulty concentrating", "daytime sleepiness"]},
  {"disease_id": "DIS015", "disease_name": "constipation",             "severity": "NORMAL",    "description": "Constipation is infrequent bowel movements or difficult passage of stools",                          "symptoms": ["infrequent bowel movements", "hard stools", "straining", "abdominal bloating", "abdominal pain", "feeling of incomplete evacuation"]}
]
